robotstxt/__init__.py
robotstxt/directive_match.py
robotstxt/processor.py
robotstxt/robots_processing.py
robotstxt/validation.py
robotstxt-1.1.2.dist-info/licenses/LICENSE
tests/__init__.py
tests/test_directive_match.py
tests/test_processor.py
tests/test_robots_compare.py
tests/test_robots_processing.py
tests/test_validation.py
robotstxt-1.1.2.dist-info/METADATA
robotstxt-1.1.2.dist-info/WHEEL
robotstxt-1.1.2.dist-info/top_level.txt
robotstxt-1.1.2.dist-info/RECORD
