Metadata-Version: 2.4
Name: robotstxt
Version: 1.1.2
Summary: A Python package to check URL paths against robots directives a robots.txt file.
Home-page: https://github.com/chrisevans77/robotstxt_package
Author: Christopher Evans
Author-email: chris@chris24.co.uk
Classifier: Programming Language :: Python :: 3
Classifier: License :: OSI Approved :: MIT License
Classifier: Operating System :: OS Independent
Requires-Python: >=3.8
License-File: LICENSE
Dynamic: author
Dynamic: author-email
Dynamic: classifier
Dynamic: description
Dynamic: description-content-type
Dynamic: home-page
Dynamic: license-file
Dynamic: requires-python
Dynamic: summary
